app/__init__.py
app/file_creation_commands.py
app/helper.py
app/main.py
py_bootstrap_cli-0.0.2.dist-info/entry_points.txt
py_bootstrap_cli-0.0.2.dist-info/LICENSE.md
py_bootstrap_cli-0.0.2.dist-info/METADATA
py_bootstrap_cli-0.0.2.dist-info/WHEEL
py_bootstrap_cli-0.0.2.dist-info/RECORD
