Metadata-Version: 2.1
Name: py-bootstrap-cli
Version: 0.0.2
Summary: 
Author: Markus Lang
Requires-Python: >=3.11,<3.13
Classifier: Programming Language :: Python :: 3
Classifier: Programming Language :: Python :: 3.11
Classifier: Programming Language :: Python :: 3.12
Requires-Dist: colorama (>=0.4.6,<0.5.0)
Requires-Dist: toml (>=0.10.2,<0.11.0)
Requires-Dist: typer (>=0.9.0,<0.10.0)
